{  
   "aircraftType":"EMB120GA",
   "liveryFileName":"EMB120GA_MOD.png",
   "pixelSize":133,
   "liveryComponent":[  
      {  
         "name":"Fuselage",
         "layerOrder":2,
         "slicePosition":{  
            "x":16,
            "y":4
         },
         "sliceSize":{  
            "x":2285,
            "y":260
         },
         "position":{  
            "x":0,
            "y":0,
            "z":0
         },
         "rotation":180
      },
      {  
         "name":"EngineLeft",
         "layerOrder":2,
         "slicePosition":{  
            "x":724,
            "y":300
         },
         "sliceSize":{  
            "x":571,
            "y":94
         },
         "position":{  
            "x":1.1009739624060150375939849624061,
            "y":2.8507218045112781954887218045112,
            "z":0
         },
         "flip":{  
            "x":0,
            "y":0
         },
         "rotation":180
      },
		{  
         "name":"EngineRight",
         "layerOrder":2,
         "slicePosition":{  
            "x":724,
            "y":423
         },
         "sliceSize":{  
            "x":571,
            "y":94
         },
         "position":{  
            "x":1.1009739624060150375939849624061,
            "y":-2.8507218045112781954887218045112,
            "z":0
         },
         "flip":{  
            "x":0,
            "y":1
         },
         "rotation":180
      },
      {  
         "name":"WingTipLeft",
         "layerOrder":3,
         "slicePosition":{  
            "x":123,
            "y":331
         },
         "sliceSize":{  
            "x":168,
            "y":33
         },
         "position":{  
            "x":0.35661306015037593984962406015038,
            "y":8.7379398496240601503759398496241,
            "z":0
         },
         "flip":{  
            "x":0,
            "y":0
         },
         "rotation":180
      },
		{  
         "name":"WingTipRight",
         "layerOrder":3,
         "slicePosition":{  
            "x":123,
            "y":422
         },
         "sliceSize":{  
            "x":168,
            "y":33
         },
         "position":{  
            "x":0.35661306015037593984962406015038,
            "y":-8.7379398496240601503759398496241,
            "z":0
         },
         "flip":{  
            "x":0,
            "y":0
         },
         "rotation":180
      },	  
		{  
         "name":"Tail",
         "layerOrder":3,
         "slicePosition":{  
            "x":1499,
            "y":276
         },
         "sliceSize":{  
            "x":957,
            "y":837
         },
         "position":{  
            "x":-6.1756165413533834586466165413534,
            "y":0,
            "z":0
         },
         "flip":{  
            "x":0,
            "y":0
         },
         "rotation":180
      }
   ]
}