{
	"id": [
		"MD87"
	],
	"copyFrom": "MD80",
	"numEngines": 2,
	"wingSpan_M": 32.82,
	"length_M": 39.75,
	"forcedReScale" : 0.9938,
	"size": 4,
	"threeStepSize": 1,
	"displayName": [
		"MD-87"
	],
	"iCAOCode": [
		"MD87"
	],
	"manufacturer": [
		"McDonnell Douglas"
	],
	"numBuilt": [
		75
	],
	"yearIntroduced": [
		1986
	],
	"yearLastProduced": [
		1992
	],
	"yearRetired": [
		2025
	],
	"capacity_PAX": [
		114
	],
	"exitLimit_PAX": [
		139
	],
	"seatsAbreast": [
		5
	],
	"capacityULDLowerDeck": [
		0
	],
	"capacityULDUpperDeck": [
		0
	],
	"capacityBulkCargo_KG": [
		2300
	],
	"range_KM": [
		5400
	],
	"speed_KMH": [
		873
	],
	"etops_Minutes": [
		60
	],
	"fuelCapacity_L": [
		18414
	],
	"engineType": [
		"low_turbofan"
	],
	"takeoffDistance_M": [
		2300
	],
	"maxTOW_KG": [
		68000
	],
	"needStairs": [
		false
	],
	"needPushback": [
		false
	],
	"needPaved": [
		true
	],
	"needHeavyPaved": [
		false
	],
	"canGetPushback": [
		true
	],
	"jetbridgePoints": [
		2
	],
	"conveyerPoints": [
		0
	],
	"cleaningPoints": [
		0
	],
	"cateringPoints": [
		1
	],
	"sonicBoom": [
		false
	],
	"vIP": [
		false
	],
	"combi": [
		false
	],
	"cargo": [
		false
	],
	"loud": [
		true
	],
	"quiet": [
		false
	]
}